processing/__init__.py
processing/combination.py
processing/transformation.py
utils/__init__.py
utils/io.py
utils/plot.py
teste_do_meu_pacote_de_imagem-0.0.8.dist-info/METADATA
teste_do_meu_pacote_de_imagem-0.0.8.dist-info/WHEEL
teste_do_meu_pacote_de_imagem-0.0.8.dist-info/top_level.txt
teste_do_meu_pacote_de_imagem-0.0.8.dist-info/RECORD
