Metadata-Version: 2.4
Name: teste_do_meu_pacote_de_imagem
Version: 0.0.8
Summary: Criando um pacote de processamento de imagem com Python
Home-page: https://github.com/Destefanir/image-processing-package
Author: Rafael
Author-email: rdestefani000@gmail.com
Requires-Python: >=3.8
Dynamic: author
Dynamic: author-email
Dynamic: description
Dynamic: description-content-type
Dynamic: home-page
Dynamic: requires-python
Dynamic: summary
